[
  {
    "fields": [
      {
        "validation": [
          {
            "level": "error",
            "rules": [
              {
                "flag": "presence",
                "constraint": "required"
              }
            ]
          }
        ],
        "name": "title",
        "type": "string"
      },
      {
        "options": {
          "source": "title",
          "maxLength": 96
        },
        "validation": [
          {
            "level": "error",
            "rules": [
              {
                "flag": "custom"
              },
              {
                "flag": "presence",
                "constraint": "required"
              }
            ]
          }
        ],
        "name": "slug",
        "type": "slug"
      },
      {
        "name": "client",
        "type": "string"
      },
      {
        "to": [
          {
            "type": "category"
          }
        ],
        "name": "category",
        "type": "reference"
      },
      {
        "name": "year",
        "type": "string"
      },
      {
        "options": {
          "hotspot": true
        },
        "validation": [
          {
            "level": "error",
            "rules": [
              {
                "flag": "presence",
                "constraint": "required"
              }
            ]
          }
        ],
        "name": "thumbnail",
        "type": "image"
      },
      {
        "options": {
          "hotspot": true
        },
        "name": "heroImage",
        "type": "image"
      },
      {
        "of": [
          {
            "lists": [
              {
                "value": "bullet",
                "title": "Bulleted list"
              },
              {
                "value": "number",
                "title": "Numbered list"
              }
            ],
            "marks": {
              "annotations": [
                {
                  "i18nTitleKey": "inputs.portable-text.annotation.link",
                  "options": {
                    "modal": {
                      "type": "popover"
                    }
                  },
                  "fields": [
                    {
                      "validation": [
                        {
                          "level": "error",
                          "rules": [
                            {
                              "flag": "uri",
                              "constraint": {
                                "options": {
                                  "scheme": [
                                    "/^http$/",
                                    "/^https$/",
                                    "/^tel$/",
                                    "/^mailto$/"
                                  ],
                                  "allowRelative": true,
                                  "relativeOnly": false,
                                  "allowCredentials": false
                                }
                              }
                            }
                          ]
                        }
                      ],
                      "description": "A valid web, email, phone, or relative link.",
                      "name": "href",
                      "type": "url",
                      "title": "Link"
                    }
                  ],
                  "name": "link",
                  "type": "object"
                }
              ],
              "decorators": [
                {
                  "value": "strong",
                  "title": "Strong"
                },
                {
                  "value": "em",
                  "title": "Italic"
                },
                {
                  "value": "code",
                  "title": "Code"
                },
                {
                  "value": "underline",
                  "title": "Underline"
                },
                {
                  "value": "strike-through",
                  "title": "Strike"
                }
              ]
            },
            "of": [],
            "styles": [
              {
                "value": "normal",
                "title": "Normal"
              },
              {
                "value": "h1",
                "title": "Heading 1"
              },
              {
                "value": "h2",
                "title": "Heading 2"
              },
              {
                "value": "h3",
                "title": "Heading 3"
              },
              {
                "value": "h4",
                "title": "Heading 4"
              },
              {
                "value": "h5",
                "title": "Heading 5"
              },
              {
                "value": "h6",
                "title": "Heading 6"
              },
              {
                "value": "blockquote",
                "title": "Quote"
              }
            ],
            "type": "block"
          },
          {
            "options": {
              "hotspot": true
            },
            "fields": [
              {
                "name": "alt",
                "type": "string",
                "title": "Alt Text"
              }
            ],
            "type": "image"
          }
        ],
        "name": "body",
        "type": "array"
      },
      {
        "of": [
          {
            "options": {
              "hotspot": true
            },
            "fields": [
              {
                "name": "alt",
                "type": "string",
                "title": "Alt Text"
              }
            ],
            "type": "image"
          }
        ],
        "name": "gallery",
        "type": "array"
      },
      {
        "initialValue": false,
        "name": "featured",
        "type": "boolean"
      },
      {
        "initialValue": 0,
        "name": "order",
        "type": "number"
      }
    ],
    "name": "project",
    "type": "document"
  },
  {
    "fields": [
      {
        "validation": [
          {
            "level": "error",
            "rules": [
              {
                "flag": "presence",
                "constraint": "required"
              }
            ]
          }
        ],
        "name": "title",
        "type": "string"
      },
      {
        "options": {
          "source": "title",
          "maxLength": 96
        },
        "validation": [
          {
            "level": "error",
            "rules": [
              {
                "flag": "custom"
              },
              {
                "flag": "presence",
                "constraint": "required"
              }
            ]
          }
        ],
        "name": "slug",
        "type": "slug"
      },
      {
        "name": "description",
        "type": "text"
      }
    ],
    "name": "category",
    "type": "document"
  },
  {
    "fields": [
      {
        "validation": [
          {
            "level": "error",
            "rules": [
              {
                "flag": "presence",
                "constraint": "required"
              }
            ]
          }
        ],
        "name": "title",
        "type": "string"
      },
      {
        "name": "description",
        "type": "text"
      },
      {
        "of": [
          {
            "type": "string"
          }
        ],
        "name": "features",
        "type": "array"
      },
      {
        "description": "Lucide icon name (e.g. 'palette', 'pen-tool', 'layers')",
        "name": "icon",
        "type": "string",
        "title": "Icon Name"
      },
      {
        "initialValue": 0,
        "name": "order",
        "type": "number"
      },
      {
        "description": "e.g. 'Starting at $500' or 'Get a Quote'",
        "name": "pricingLabel",
        "type": "string"
      }
    ],
    "name": "service",
    "type": "document"
  },
  {
    "fields": [
      {
        "validation": [
          {
            "level": "error",
            "rules": [
              {
                "flag": "presence",
                "constraint": "required"
              }
            ]
          }
        ],
        "name": "clientName",
        "type": "string"
      },
      {
        "name": "role",
        "type": "string"
      },
      {
        "name": "company",
        "type": "string"
      },
      {
        "validation": [
          {
            "level": "error",
            "rules": [
              {
                "flag": "presence",
                "constraint": "required"
              }
            ]
          }
        ],
        "name": "quote",
        "type": "text"
      },
      {
        "options": {
          "hotspot": true
        },
        "name": "avatar",
        "type": "image"
      },
      {
        "initialValue": false,
        "name": "featured",
        "type": "boolean"
      }
    ],
    "name": "testimonial",
    "type": "document"
  },
  {
    "fields": [
      {
        "validation": [
          {
            "level": "error",
            "rules": [
              {
                "flag": "presence",
                "constraint": "required"
              }
            ]
          }
        ],
        "name": "name",
        "type": "string"
      },
      {
        "name": "tagline",
        "type": "string"
      },
      {
        "description": "Brief bio for the home page",
        "name": "bio",
        "type": "text",
        "title": "Short Bio"
      },
      {
        "description": "Full about page content",
        "of": [
          {
            "lists": [
              {
                "value": "bullet",
                "title": "Bulleted list"
              },
              {
                "value": "number",
                "title": "Numbered list"
              }
            ],
            "marks": {
              "annotations": [
                {
                  "i18nTitleKey": "inputs.portable-text.annotation.link",
                  "options": {
                    "modal": {
                      "type": "popover"
                    }
                  },
                  "fields": [
                    {
                      "validation": [
                        {
                          "level": "error",
                          "rules": [
                            {
                              "flag": "uri",
                              "constraint": {
                                "options": {
                                  "scheme": [
                                    "/^http$/",
                                    "/^https$/",
                                    "/^tel$/",
                                    "/^mailto$/"
                                  ],
                                  "allowRelative": true,
                                  "relativeOnly": false,
                                  "allowCredentials": false
                                }
                              }
                            }
                          ]
                        }
                      ],
                      "description": "A valid web, email, phone, or relative link.",
                      "name": "href",
                      "type": "url",
                      "title": "Link"
                    }
                  ],
                  "name": "link",
                  "type": "object"
                }
              ],
              "decorators": [
                {
                  "value": "strong",
                  "title": "Strong"
                },
                {
                  "value": "em",
                  "title": "Italic"
                },
                {
                  "value": "code",
                  "title": "Code"
                },
                {
                  "value": "underline",
                  "title": "Underline"
                },
                {
                  "value": "strike-through",
                  "title": "Strike"
                }
              ]
            },
            "of": [],
            "styles": [
              {
                "value": "normal",
                "title": "Normal"
              },
              {
                "value": "h1",
                "title": "Heading 1"
              },
              {
                "value": "h2",
                "title": "Heading 2"
              },
              {
                "value": "h3",
                "title": "Heading 3"
              },
              {
                "value": "h4",
                "title": "Heading 4"
              },
              {
                "value": "h5",
                "title": "Heading 5"
              },
              {
                "value": "h6",
                "title": "Heading 6"
              },
              {
                "value": "blockquote",
                "title": "Quote"
              }
            ],
            "type": "block"
          }
        ],
        "name": "aboutText",
        "type": "array"
      },
      {
        "options": {
          "hotspot": true
        },
        "name": "portrait",
        "type": "image"
      },
      {
        "options": {
          "list": [
            {
              "title": "Available for Freelance",
              "value": "available"
            },
            {
              "title": "Limited Availability",
              "value": "limited"
            },
            {
              "title": "Not Available",
              "value": "unavailable"
            }
          ]
        },
        "initialValue": "available",
        "name": "availabilityStatus",
        "type": "string"
      },
      {
        "name": "email",
        "type": "string"
      },
      {
        "name": "phone",
        "type": "string"
      },
      {
        "name": "location",
        "type": "string"
      },
      {
        "of": [
          {
            "fields": [
              {
                "name": "platform",
                "type": "string"
              },
              {
                "validation": [
                  {
                    "level": "error",
                    "rules": [
                      {
                        "flag": "uri",
                        "constraint": {
                          "options": {
                            "scheme": [
                              "/^http$/",
                              "/^https$/"
                            ],
                            "allowRelative": false,
                            "relativeOnly": false,
                            "allowCredentials": false
                          }
                        }
                      }
                    ]
                  }
                ],
                "name": "url",
                "type": "url",
                "title": "URL"
              }
            ],
            "type": "object"
          }
        ],
        "name": "socialLinks",
        "type": "array"
      },
      {
        "validation": [
          {
            "level": "error",
            "rules": [
              {
                "flag": "uri",
                "constraint": {
                  "options": {
                    "scheme": [
                      "/^http$/",
                      "/^https$/"
                    ],
                    "allowRelative": false,
                    "relativeOnly": false,
                    "allowCredentials": false
                  }
                }
              }
            ]
          }
        ],
        "name": "behanceUrl",
        "type": "url",
        "title": "Behance URL"
      },
      {
        "name": "resumeFile",
        "type": "file"
      }
    ],
    "name": "siteSettings",
    "type": "document"
  }
]